{
    "documents": [
        {
            "address_name": "경기 가평군 설악면 가일리 308-18",
            "category_group_code": "CE7",
            "category_group_name": "카페",
            "category_name": "음식점 > 카페",
            "distance": "4991",
            "id": "1477106873",
            "phone": "031-584-1632",
            "place_name": "카페밸리",
            "place_url": "http://place.map.kakao.com/1477106873",
            "road_address_name": "경기 가평군 설악면 유명로 626",
            "x": "127.49353895983387",
            "y": "37.60218529896021"
        },
        {
            "address_name": "경기 가평군 설악면 가일리 193-12",
            "category_group_code": "CE7",
            "category_group_name": "카페",
            "category_name": "음식점 > 카페",
            "distance": "4936",
            "id": "982455470",
            "phone": "",
            "place_name": "으아리카페",
            "place_url": "http://place.map.kakao.com/982455470",
            "road_address_name": "경기 가평군 설악면 어비산길 16",
            "x": "127.494105497085",
            "y": "37.5994943979754"
        },
        {
            "address_name": "경기 가평군 설악면 가일리 255",
            "category_group_code": "CE7",
            "category_group_name": "카페",
            "category_name": "음식점 > 카페",
            "distance": "5243",
            "id": "865890827",
            "phone": "",
            "place_name": "까페몽실언니",
            "place_url": "http://place.map.kakao.com/865890827",
            "road_address_name": "경기 가평군 설악면 유명산길 79-17",
            "x": "127.491033089729",
            "y": "37.5944617173945"
        },
        {
            "address_name": "경기 가평군 설악면 위곡리 303-3",
            "category_group_code": "CE7",
            "category_group_name": "카페",
            "category_name": "음식점 > 카페",
            "distance": "7227",
            "id": "785155244",
            "phone": "031-580-3804",
            "place_name": "나인블럭 가평점",
            "place_url": "http://place.map.kakao.com/785155244",
            "road_address_name": "경기 가평군 설악면 한서로268번길 157",
            "x": "127.524365970693",
            "y": "37.6618411420287"
        },
        {
            "address_name": "경기 가평군 설악면 방일리 228",
            "category_group_code": "CE7",
            "category_group_name": "카페",
            "category_name": "음식점 > 카페",
            "distance": "5515",
            "id": "26535312",
            "phone": "031-584-8838",
            "place_name": "농부들의카페장터",
            "place_url": "http://place.map.kakao.com/26535312",
            "road_address_name": "경기 가평군 설악면 유명로 891",
            "x": "127.494673788519",
            "y": "37.6230652698668"
        },
        {
            "address_name": "경기 가평군 설악면 가일리 230",
            "category_group_code": "CE7",
            "category_group_name": "카페",
            "category_name": "음식점 > 카페 > 커피전문점",
            "distance": "5371",
            "id": "18754417",
            "phone": "",
            "place_name": "오렌지루프커피",
            "place_url": "http://place.map.kakao.com/18754417",
            "road_address_name": "경기 가평군 설악면 유명산길 79-76",
            "x": "127.489958718257",
            "y": "37.5922461593035"
        },
        {
            "address_name": "경기 가평군 설악면 위곡리 303-3",
            "category_group_code": "CE7",
            "category_group_name": "카페",
            "category_name": "음식점 > 카페",
            "distance": "7210",
            "id": "1938024934",
            "phone": "031-580-3800",
            "place_name": "나인블럭 키친",
            "place_url": "http://place.map.kakao.com/1938024934",
            "road_address_name": "경기 가평군 설악면 한서로268번길 157",
            "x": "127.52431942839307",
            "y": "37.66166926332435"
        },
        {
            "address_name": "경기 양평군 용문면 오촌리 160-3",
            "category_group_code": "CE7",
            "category_group_name": "카페",
            "category_name": "음식점 > 카페 > 테마카페 > 디저트카페",
            "distance": "7613",
            "id": "1288125279",
            "phone": "031-773-0722",
            "place_name": "구름정원제빵소",
            "place_url": "http://place.map.kakao.com/1288125279",
            "road_address_name": "경기 양평군 용문면 용문산로 543",
            "x": "127.588261736606",
            "y": "37.5385345905134"
        },
        {
            "address_name": "경기 가평군 설악면 가일리 226-1",
            "category_group_code": "CE7",
            "category_group_name": "카페",
            "category_name": "음식점 > 카페",
            "distance": "5524",
            "id": "1431061967",
            "phone": "",
            "place_name": "산카페",
            "place_url": "http://place.map.kakao.com/1431061967",
            "road_address_name": "경기 가평군 설악면 유명산길 114",
            "x": "127.488127157788",
            "y": "37.5926645966486"
        },
        {
            "address_name": "경기 양평군 용문면 신점리 334",
            "category_group_code": "CE7",
            "category_group_name": "카페",
            "category_name": "음식점 > 카페 > 테마카페 > 디저트카페",
            "distance": "7365",
            "id": "1715016966",
            "phone": "",
            "place_name": "카페비아지오",
            "place_url": "http://place.map.kakao.com/1715016966",
            "road_address_name": "경기 양평군 용문면 용문산로 567-5",
            "x": "127.587051045239",
            "y": "37.5405516202133"
        },
        {
            "address_name": "경기 양평군 단월면 석산리 218",
            "category_group_code": "CE7",
            "category_group_name": "카페",
            "category_name": "음식점 > 카페 > 테마카페 > 디저트카페",
            "distance": "6683",
            "id": "950209223",
            "phone": "031-771-1227",
            "place_name": "자그마치",
            "place_url": "http://place.map.kakao.com/950209223",
            "road_address_name": "경기 양평군 단월면 석산로 1423",
            "x": "127.60570413770816",
            "y": "37.64077604808009"
        },
        {
            "address_name": "경기 가평군 설악면 방일리 716",
            "category_group_code": "CE7",
            "category_group_name": "카페",
            "category_name": "음식점 > 카페",
            "distance": "6825",
            "id": "475375960",
            "phone": "031-589-3321",
            "place_name": "맥퀸즈카페",
            "place_url": "http://place.map.kakao.com/475375960",
            "road_address_name": "경기 가평군 설악면 유명로 1007-90",
            "x": "127.47995684698152",
            "y": "37.626015488842384"
        },
        {
            "address_name": "경기 양평군 용문면 신점리 519-5",
            "category_group_code": "CE7",
            "category_group_name": "카페",
            "category_name": "음식점 > 카페",
            "distance": "6620",
            "id": "1985826994",
            "phone": "070-4459-5370",
            "place_name": "아이갓에브리씽 양평점",
            "place_url": "http://place.map.kakao.com/1985826994",
            "road_address_name": "경기 양평군 용문면 용문산로 655",
            "x": "127.582170132093",
            "y": "37.5461258669466"
        },
        {
            "address_name": "경기 양평군 옥천면 용천리 182-3",
            "category_group_code": "CE7",
            "category_group_name": "카페",
            "category_name": "음식점 > 카페",
            "distance": "8353",
            "id": "1419268064",
            "phone": "031-774-3652",
            "place_name": "카페마카우",
            "place_url": "http://place.map.kakao.com/1419268064",
            "road_address_name": "경기 양평군 옥천면 용천로 206",
            "x": "127.494069037766",
            "y": "37.5393131353204"
        },
        {
            "address_name": "경기 가평군 설악면 가일리 413",
            "category_group_code": "CE7",
            "category_group_name": "카페",
            "category_name": "음식점 > 카페",
            "distance": "6904",
            "id": "13090426",
            "phone": "031-584-7739",
            "place_name": "금수강산",
            "place_url": "http://place.map.kakao.com/13090426",
            "road_address_name": "",
            "x": "127.472675499915",
            "y": "37.5907993815422"
        }
    ],
    "meta": {
        "is_end": false,
        "pageable_count": 45,
        "same_name": null,
        "total_count": 116935
    }
}