{
    "documents": [
        {
            "address_name": "경기 연천군 청산면 궁평리 562-6",
            "category_group_code": "CE7",
            "category_group_name": "카페",
            "category_name": "음식점 > 카페 > 테마카페 > 디저트카페",
            "distance": "1670",
            "id": "1057328412",
            "phone": "031-5177-9979",
            "place_name": "라피유",
            "place_url": "http://place.map.kakao.com/1057328412",
            "road_address_name": "경기 연천군 청산면 청연로 34",
            "x": "127.10367302008146",
            "y": "38.035228277950026"
        },
        {
            "address_name": "경기 연천군 청산면 궁평리 489-18",
            "category_group_code": "CE7",
            "category_group_name": "카페",
            "category_name": "음식점 > 카페",
            "distance": "2321",
            "id": "260754658",
            "phone": "",
            "place_name": "백인더처치",
            "place_url": "http://place.map.kakao.com/260754658",
            "road_address_name": "경기 연천군 청산면 궁평로 71-1",
            "x": "127.107748945683",
            "y": "38.0299983525019"
        },
        {
            "address_name": "경기 연천군 청산면 궁평리 165-13",
            "category_group_code": "CE7",
            "category_group_name": "카페",
            "category_name": "음식점 > 카페 > 다방",
            "distance": "2268",
            "id": "21498222",
            "phone": "031-835-5092",
            "place_name": "비서실다방",
            "place_url": "http://place.map.kakao.com/21498222",
            "road_address_name": "경기 연천군 청산면 궁평로91번길 4",
            "x": "127.109431552599",
            "y": "38.0309734005684"
        },
        {
            "address_name": "경기 연천군 청산면 궁평리 232",
            "category_group_code": "CE7",
            "category_group_name": "카페",
            "category_name": "음식점 > 카페",
            "distance": "2936",
            "id": "1005441353",
            "phone": "",
            "place_name": "카페리히트",
            "place_url": "http://place.map.kakao.com/1005441353",
            "road_address_name": "경기 연천군 청산면 궁평로 13",
            "x": "127.109271707564",
            "y": "38.024580586623"
        },
        {
            "address_name": "경기 연천군 전곡읍 전곡리 367-5",
            "category_group_code": "CE7",
            "category_group_name": "카페",
            "category_name": "음식점 > 카페",
            "distance": "3284",
            "id": "181999750",
            "phone": "",
            "place_name": "마루",
            "place_url": "http://place.map.kakao.com/181999750",
            "road_address_name": "경기 연천군 전곡읍 선사로 456",
            "x": "127.072603960768",
            "y": "38.0298415185142"
        },
        {
            "address_name": "경기 연천군 청산면 궁평리 232",
            "category_group_code": "CE7",
            "category_group_name": "카페",
            "category_name": "음식점 > 카페",
            "distance": "2936",
            "id": "21344802",
            "phone": "031-833-8490",
            "place_name": "더카페",
            "place_url": "http://place.map.kakao.com/21344802",
            "road_address_name": "경기 연천군 청산면 궁평로 13",
            "x": "127.109271707564",
            "y": "38.024580586623"
        },
        {
            "address_name": "경기 연천군 전곡읍 전곡리 462-19",
            "category_group_code": "CE7",
            "category_group_name": "카페",
            "category_name": "음식점 > 카페 > 커피전문점 > 이디야커피",
            "distance": "3839",
            "id": "18295028",
            "phone": "031-832-0095",
            "place_name": "이디야커피 전곡역점",
            "place_url": "http://place.map.kakao.com/18295028",
            "road_address_name": "경기 연천군 전곡읍 전곡로 156",
            "x": "127.068440834692",
            "y": "38.026052922937"
        },
        {
            "address_name": "경기 연천군 전곡읍 전곡리 462-16",
            "category_group_code": "CE7",
            "category_group_name": "카페",
            "category_name": "음식점 > 카페 > 커피전문점 > 메가커피",
            "distance": "3830",
            "id": "406120351",
            "phone": "031-833-3336",
            "place_name": "메가커피 연천전곡점",
            "place_url": "http://place.map.kakao.com/406120351",
            "road_address_name": "경기 연천군 전곡읍 전곡로 158",
            "x": "127.06833623691",
            "y": "38.0262511873455"
        },
        {
            "address_name": "경기 연천군 전곡읍 전곡리 386-3",
            "category_group_code": "CE7",
            "category_group_name": "카페",
            "category_name": "음식점 > 카페",
            "distance": "3242",
            "id": "67785074",
            "phone": "02-403-0554",
            "place_name": "빈트리 전곡점",
            "place_url": "http://place.map.kakao.com/67785074",
            "road_address_name": "경기 연천군 전곡읍 전은길 15",
            "x": "127.07122300912866",
            "y": "38.03168565487943"
        },
        {
            "address_name": "경기 연천군 전곡읍 전곡리 468-11",
            "category_group_code": "CE7",
            "category_group_name": "카페",
            "category_name": "음식점 > 카페 > 테마카페 > 디저트카페 > 설빙",
            "distance": "3903",
            "id": "27596168",
            "phone": "031-832-6040",
            "place_name": "설빙 연천전곡점",
            "place_url": "http://place.map.kakao.com/27596168",
            "road_address_name": "경기 연천군 전곡읍 전곡로 145",
            "x": "127.06861760085688",
            "y": "38.025079820466644"
        },
        {
            "address_name": "경기 연천군 전곡읍 전곡리 344-52",
            "category_group_code": "CE7",
            "category_group_name": "카페",
            "category_name": "음식점 > 카페",
            "distance": "3497",
            "id": "800315798",
            "phone": "070-7802-6570",
            "place_name": "가드닝카페 온실",
            "place_url": "http://place.map.kakao.com/800315798",
            "road_address_name": "경기 연천군 전곡읍 은전로91번길 26",
            "x": "127.06936012494",
            "y": "38.0298578916311"
        },
        {
            "address_name": "경기 연천군 전곡읍 전곡리 305-24",
            "category_group_code": "CE7",
            "category_group_name": "카페",
            "category_name": "음식점 > 카페 > 테마카페 > 디저트카페 > 디저트39",
            "distance": "3949",
            "id": "159179392",
            "phone": "031-835-7739",
            "place_name": "디저트39 연천전곡점",
            "place_url": "http://place.map.kakao.com/159179392",
            "road_address_name": "경기 연천군 전곡읍 온골로 38-2",
            "x": "127.068603403773",
            "y": "38.0245113447401"
        },
        {
            "address_name": "경기 연천군 전곡읍 전곡리 485-34",
            "category_group_code": "CE7",
            "category_group_name": "카페",
            "category_name": "음식점 > 카페",
            "distance": "3996",
            "id": "762033313",
            "phone": "",
            "place_name": "루쏘",
            "place_url": "http://place.map.kakao.com/762033313",
            "road_address_name": "경기 연천군 전곡읍 온골로43번길 8",
            "x": "127.06757402971866",
            "y": "38.02472996480718"
        },
        {
            "address_name": "경기 연천군 전곡읍 전곡리 480-15",
            "category_group_code": "CE7",
            "category_group_name": "카페",
            "category_name": "음식점 > 카페 > 커피전문점 > 카페베네",
            "distance": "3871",
            "id": "26557899",
            "phone": "031-833-0055",
            "place_name": "카페베네 전곡터미널점",
            "place_url": "http://place.map.kakao.com/26557899",
            "road_address_name": "경기 연천군 전곡읍 온골로 59-1",
            "x": "127.0676802227194",
            "y": "38.02626598158586"
        },
        {
            "address_name": "경기 연천군 전곡읍 전곡리 333-167",
            "category_group_code": "CE7",
            "category_group_name": "카페",
            "category_name": "음식점 > 카페 > 다방",
            "distance": "3731",
            "id": "21175791",
            "phone": "031-835-4321",
            "place_name": "금다방",
            "place_url": "http://place.map.kakao.com/21175791",
            "road_address_name": "경기 연천군 전곡읍 전곡로164번길 19",
            "x": "127.068988414854",
            "y": "38.0270039800089"
        }
    ],
    "meta": {
        "is_end": false,
        "pageable_count": 45,
        "same_name": null,
        "total_count": 116935
    }
}