{
    "documents": [
        {
            "address_name": "경남 함양군 마천면 추성리 353-2",
            "category_group_code": "CE7",
            "category_group_name": "카페",
            "category_name": "음식점 > 카페 > 커피전문점",
            "distance": "4287",
            "id": "1280665842",
            "phone": "",
            "place_name": "카페롤로",
            "place_url": "http://place.map.kakao.com/1280665842",
            "road_address_name": "경남 함양군 마천면 칠선로 231-7",
            "x": "127.696293843327",
            "y": "35.3885207398029"
        },
        {
            "address_name": "경남 함양군 마천면 덕전리 383-2",
            "category_group_code": "CE7",
            "category_group_name": "카페",
            "category_name": "음식점 > 카페",
            "distance": "4365",
            "id": "232445379",
            "phone": "",
            "place_name": "무인카페 꽃자갈",
            "place_url": "http://place.map.kakao.com/232445379",
            "road_address_name": "경남 함양군 마천면 마천삼정로 291",
            "x": "127.659581460543",
            "y": "35.3712594249186"
        },
        {
            "address_name": "경남 함양군 마천면 군자리 93-1",
            "category_group_code": "CE7",
            "category_group_name": "카페",
            "category_name": "음식점 > 카페 > 커피전문점",
            "distance": "6159",
            "id": "27299933",
            "phone": "070-8843-3245",
            "place_name": "커피줄라이",
            "place_url": "http://place.map.kakao.com/27299933",
            "road_address_name": "경남 함양군 마천면 덕전길 4",
            "x": "127.659966768258",
            "y": "35.394792235789"
        },
        {
            "address_name": "경남 함양군 마천면 군자리 50-9",
            "category_group_code": "CE7",
            "category_group_name": "카페",
            "category_name": "음식점 > 카페 > 다방",
            "distance": "6333",
            "id": "10078714",
            "phone": "055-963-5989",
            "place_name": "용궁다방",
            "place_url": "http://place.map.kakao.com/10078714",
            "road_address_name": "경남 함양군 마천면 군자길 18",
            "x": "127.659942771104",
            "y": "35.3967103430746"
        },
        {
            "address_name": "경남 함양군 마천면 가흥리 529-7",
            "category_group_code": "CE7",
            "category_group_name": "카페",
            "category_name": "음식점 > 카페 > 다방",
            "distance": "6082",
            "id": "21481019",
            "phone": "055-962-0085",
            "place_name": "상록수다방",
            "place_url": "http://place.map.kakao.com/21481019",
            "road_address_name": "경남 함양군 마천면 천왕봉로 1163",
            "x": "127.664807379855",
            "y": "35.3966259856763"
        },
        {
            "address_name": "경남 함양군 마천면 창원리 1063",
            "category_group_code": "CE7",
            "category_group_name": "카페",
            "category_name": "음식점 > 카페",
            "distance": "8405",
            "id": "1290985328",
            "phone": "010-2033-1001",
            "place_name": "마을카페안녕",
            "place_url": "http://place.map.kakao.com/1290985328",
            "road_address_name": "경남 함양군 마천면 창원아랫길 25-14",
            "x": "127.67767779828257",
            "y": "35.423514196852864"
        },
        {
            "address_name": "경남 함양군 마천면 가흥리 595",
            "category_group_code": "CE7",
            "category_group_name": "카페",
            "category_name": "음식점 > 카페",
            "distance": "6047",
            "id": "8196144",
            "phone": "",
            "place_name": "그린다방",
            "place_url": "http://place.map.kakao.com/8196144",
            "road_address_name": "경남 함양군 마천면 천왕봉로 1164",
            "x": "127.66489723387",
            "y": "35.3963082320642"
        },
        {
            "address_name": "경남 산청군 시천면 중산리 722-2",
            "category_group_code": "CE7",
            "category_group_name": "카페",
            "category_name": "음식점 > 카페 > 테마카페 > 라이브카페",
            "distance": "7789",
            "id": "103644158",
            "phone": "055-974-4646",
            "place_name": "새",
            "place_url": "http://place.map.kakao.com/103644158",
            "road_address_name": "경남 산청군 시천면 지리산대로 482",
            "x": "127.753234842799",
            "y": "35.2949984643459"
        },
        {
            "address_name": "경남 산청군 시천면 중산리 531-19",
            "category_group_code": "CE7",
            "category_group_name": "카페",
            "category_name": "음식점 > 카페",
            "distance": "7887",
            "id": "25430945",
            "phone": "055-973-2797",
            "place_name": "카페테리아 공감",
            "place_url": "http://place.map.kakao.com/25430945",
            "road_address_name": "경남 산청군 시천면 지리산대로 497-8",
            "x": "127.75390126059",
            "y": "35.2943093140039"
        },
        {
            "address_name": "경남 하동군 화개면 대성리 1385-4",
            "category_group_code": "CE7",
            "category_group_name": "카페",
            "category_name": "음식점 > 카페",
            "distance": "8346",
            "id": "14560786",
            "phone": "010-5584-1310",
            "place_name": "지리산화개깊은골",
            "place_url": "http://place.map.kakao.com/14560786",
            "road_address_name": "경남 하동군 화개면 화개로 1435",
            "x": "127.645278322437",
            "y": "35.2895981873656"
        },
        {
            "address_name": "경남 하동군 화개면 대성리 1356-1",
            "category_group_code": "CE7",
            "category_group_name": "카페",
            "category_name": "음식점 > 카페",
            "distance": "8305",
            "id": "1950152374",
            "phone": "",
            "place_name": "노닥노닥곰다방",
            "place_url": "http://place.map.kakao.com/1950152374",
            "road_address_name": "경남 하동군 화개면 의신길 3-2",
            "x": "127.648043632996",
            "y": "35.2884297124547"
        },
        {
            "address_name": "경남 하동군 화개면 대성리 1378-20",
            "category_group_code": "CE7",
            "category_group_name": "카페",
            "category_name": "음식점 > 카페",
            "distance": "8356",
            "id": "117821543",
            "phone": "",
            "place_name": "지리산 힐링피아",
            "place_url": "http://place.map.kakao.com/117821543",
            "road_address_name": "경남 하동군 화개면 화개로 1435",
            "x": "127.645459095114",
            "y": "35.289382708416"
        },
        {
            "address_name": "전북 남원시 산내면 백일리 510-1",
            "category_group_code": "CE7",
            "category_group_name": "카페",
            "category_name": "음식점 > 카페",
            "distance": "9410",
            "id": "196485983",
            "phone": "070-7778-2431",
            "place_name": "소풍",
            "place_url": "http://place.map.kakao.com/196485983",
            "road_address_name": "",
            "x": "127.638454000474",
            "y": "35.4182119720474"
        },
        {
            "address_name": "전북 남원시 산내면 대정리 641-14",
            "category_group_code": "CE7",
            "category_group_name": "카페",
            "category_name": "음식점 > 카페",
            "distance": "10152",
            "id": "19030111",
            "phone": "070-4123-2012",
            "place_name": "마을카페 토닥",
            "place_url": "http://place.map.kakao.com/19030111",
            "road_address_name": "전북 남원시 산내면 대정길 127",
            "x": "127.628472714645",
            "y": "35.4202940608411"
        },
        {
            "address_name": "경남 하동군 화개면 삼신리 341-3",
            "category_group_code": "CE7",
            "category_group_name": "카페",
            "category_name": "음식점 > 카페",
            "distance": "15931",
            "id": "1443176232",
            "phone": "070-4458-4650",
            "place_name": "더로드101",
            "place_url": "http://place.map.kakao.com/1443176232",
            "road_address_name": "경남 하동군 화개면 화개로 357",
            "x": "127.637563937164",
            "y": "35.2158456502446"
        }
    ],
    "meta": {
        "is_end": false,
        "pageable_count": 45,
        "same_name": null,
        "total_count": 116935
    }
}