{
    "documents": [
        {
            "address_name": "충북 제천시 청풍면 연곡리 183-8",
            "category_group_code": "CE7",
            "category_group_name": "카페",
            "category_name": "음식점 > 카페",
            "distance": "1085",
            "id": "1447865387",
            "phone": "",
            "place_name": "모단",
            "place_url": "http://place.map.kakao.com/1447865387",
            "road_address_name": "충북 제천시 청풍면 청풍명월로1길 73",
            "x": "128.1540987883",
            "y": "37.0092115558571"
        },
        {
            "address_name": "충북 제천시 청풍면 도곡리 산 2-3",
            "category_group_code": "CE7",
            "category_group_name": "카페",
            "category_name": "음식점 > 카페",
            "distance": "1138",
            "id": "1925381183",
            "phone": "043-643-1421",
            "place_name": "그릿918",
            "place_url": "http://place.map.kakao.com/1925381183",
            "road_address_name": "충북 제천시 청풍면 문화재길 166-1",
            "x": "128.143222192239",
            "y": "37.0087005279054"
        },
        {
            "address_name": "충북 제천시 청풍면 물태리 133-74",
            "category_group_code": "CE7",
            "category_group_name": "카페",
            "category_name": "음식점 > 카페",
            "distance": "1460",
            "id": "676643481",
            "phone": "043-645-1131",
            "place_name": "카페슬로비",
            "place_url": "http://place.map.kakao.com/676643481",
            "road_address_name": "충북 제천시 청풍면 배시론로 18",
            "x": "128.166221597207",
            "y": "36.998035601827"
        },
        {
            "address_name": "충북 제천시 청풍면 도곡리 99",
            "category_group_code": "CE7",
            "category_group_name": "카페",
            "category_name": "음식점 > 카페",
            "distance": "1463",
            "id": "1810954557",
            "phone": "",
            "place_name": "카페붐",
            "place_url": "http://place.map.kakao.com/1810954557",
            "road_address_name": "충북 제천시 청풍면 청풍명월로 879-17",
            "x": "128.13403030202",
            "y": "37.0031518619631"
        },
        {
            "address_name": "충북 제천시 청풍면 교리 99",
            "category_group_code": "CE7",
            "category_group_name": "카페",
            "category_name": "음식점 > 카페 > 커피전문점",
            "distance": "3058",
            "id": "21312009",
            "phone": "",
            "place_name": "청풍리조트레이크피아커피숍",
            "place_url": "http://place.map.kakao.com/21312009",
            "road_address_name": "충북 제천시 청풍면 청풍호로 1798",
            "x": "128.17717475035673",
            "y": "37.016859877223816"
        },
        {
            "address_name": "충북 제천시 청풍면 교리 147",
            "category_group_code": "CE7",
            "category_group_name": "카페",
            "category_name": "음식점 > 카페",
            "distance": "2968",
            "id": "9611708",
            "phone": "043-651-2300",
            "place_name": "홍민의집",
            "place_url": "http://place.map.kakao.com/9611708",
            "road_address_name": "충북 제천시 청풍면 청풍호로50길 6",
            "x": "128.179620938283",
            "y": "37.0122835959166"
        },
        {
            "address_name": "충북 제천시 청풍면 학현리 414-5",
            "category_group_code": "CE7",
            "category_group_name": "카페",
            "category_name": "음식점 > 카페",
            "distance": "4193",
            "id": "20437355",
            "phone": "",
            "place_name": "퍼플 테라스",
            "place_url": "http://place.map.kakao.com/20437355",
            "road_address_name": "충북 제천시 청풍면 옥순봉로14길 181",
            "x": "128.196203889262",
            "y": "37.007356570818"
        },
        {
            "address_name": "충북 제천시 금성면 월굴리 177",
            "category_group_code": "CE7",
            "category_group_name": "카페",
            "category_name": "음식점 > 카페",
            "distance": "4928",
            "id": "1844715183",
            "phone": "043-646-0573",
            "place_name": "호수가에이야기",
            "place_url": "http://place.map.kakao.com/1844715183",
            "road_address_name": "충북 제천시 금성면 청풍호로 1412",
            "x": "128.17458831632922",
            "y": "37.03978417125664"
        },
        {
            "address_name": "충북 제천시 수산면 능강리 561-20",
            "category_group_code": "CE7",
            "category_group_name": "카페",
            "category_name": "음식점 > 카페",
            "distance": "5088",
            "id": "63237774",
            "phone": "0507-1344-2290",
            "place_name": "카페하인츠 제천점",
            "place_url": "http://place.map.kakao.com/63237774",
            "road_address_name": "충북 제천시 수산면 옥순봉로10길 2",
            "x": "128.201794821938",
            "y": "36.9806188390405"
        },
        {
            "address_name": "충북 제천시 청풍면 학현리 347",
            "category_group_code": "CE7",
            "category_group_name": "카페",
            "category_name": "음식점 > 카페 > 테마카페",
            "distance": "5043",
            "id": "455217017",
            "phone": "043-652-6523",
            "place_name": "족욕카페 마루",
            "place_url": "http://place.map.kakao.com/455217017",
            "road_address_name": "충북 제천시 청풍면 학현소야로 207-16",
            "x": "128.20554103103314",
            "y": "37.00898214490927"
        },
        {
            "address_name": "충북 제천시 금성면 월굴리 76-3",
            "category_group_code": "CE7",
            "category_group_name": "카페",
            "category_name": "음식점 > 카페",
            "distance": "5726",
            "id": "21531322",
            "phone": "043-652-1564",
            "place_name": "커피라끄",
            "place_url": "http://place.map.kakao.com/21531322",
            "road_address_name": "충북 제천시 금성면 청풍호로 1226",
            "x": "128.170717205643",
            "y": "37.0488488893701"
        },
        {
            "address_name": "충북 제천시 청풍면 학현리 261-1",
            "category_group_code": "CE7",
            "category_group_name": "카페",
            "category_name": "음식점 > 카페",
            "distance": "7355",
            "id": "26593665",
            "phone": "",
            "place_name": "소나무정원",
            "place_url": "http://place.map.kakao.com/26593665",
            "road_address_name": "충북 제천시 청풍면 학현소야로 457",
            "x": "128.23087647462145",
            "y": "37.013598401432"
        },
        {
            "address_name": "충북 제천시 금성면 구룡리 86",
            "category_group_code": "CE7",
            "category_group_name": "카페",
            "category_name": "음식점 > 카페",
            "distance": "7187",
            "id": "27357760",
            "phone": "",
            "place_name": "카페트리",
            "place_url": "http://place.map.kakao.com/27357760",
            "road_address_name": "충북 제천시 금성면 청풍호로 1029",
            "x": "128.167470672369",
            "y": "37.0632215537831"
        },
        {
            "address_name": "충북 제천시 금성면 구룡리 81-5",
            "category_group_code": "CE7",
            "category_group_name": "카페",
            "category_name": "음식점 > 카페 > 다방",
            "distance": "7103",
            "id": "21451386",
            "phone": "",
            "place_name": "금성다방",
            "place_url": "http://place.map.kakao.com/21451386",
            "road_address_name": "충북 제천시 금성면 청풍호로33길 6-11",
            "x": "128.167642769795",
            "y": "37.0624197529075"
        },
        {
            "address_name": "충북 충주시 동량면 지동리 364",
            "category_group_code": "CE7",
            "category_group_name": "카페",
            "category_name": "음식점 > 카페 > 전통찻집",
            "distance": "8035",
            "id": "10456950",
            "phone": "",
            "place_name": "산과물이만나는곳",
            "place_url": "http://place.map.kakao.com/10456950",
            "road_address_name": "충북 충주시 동량면 미라실로 838",
            "x": "128.059798671732",
            "y": "37.0028720399175"
        }
    ],
    "meta": {
        "is_end": false,
        "pageable_count": 45,
        "same_name": null,
        "total_count": 116935
    }
}