{
    "documents": [
        {
            "address_name": "강원 평창군 진부면 송정리 2258-29",
            "category_group_code": "CE7",
            "category_group_name": "카페",
            "category_name": "음식점 > 카페 > 커피전문점",
            "distance": "4909",
            "id": "13052883",
            "phone": "033-335-4050",
            "place_name": "엘림커피",
            "place_url": "http://place.map.kakao.com/13052883",
            "road_address_name": "강원 평창군 진부면 땅골길 2-57",
            "x": "128.557271199815",
            "y": "37.6282975157187"
        },
        {
            "address_name": "강원 평창군 진부면 하진부리 136",
            "category_group_code": "CE7",
            "category_group_name": "카페",
            "category_name": "음식점 > 카페",
            "distance": "5508",
            "id": "16274039",
            "phone": "033-336-1780",
            "place_name": "커피트리",
            "place_url": "http://place.map.kakao.com/16274039",
            "road_address_name": "강원 평창군 진부면 청송로 104",
            "x": "128.55781503166",
            "y": "37.63654978948155"
        },
        {
            "address_name": "강원 평창군 진부면 하진부리 100-23",
            "category_group_code": "CE7",
            "category_group_name": "카페",
            "category_name": "음식점 > 카페",
            "distance": "5463",
            "id": "221170336",
            "phone": "070-7727-0662",
            "place_name": "굴리엘모 진부점",
            "place_url": "http://place.map.kakao.com/221170336",
            "road_address_name": "강원 평창군 진부면 청송로 109",
            "x": "128.558751257706",
            "y": "37.6366815652033"
        },
        {
            "address_name": "강원 평창군 진부면 하진부리 138-1",
            "category_group_code": "CE7",
            "category_group_name": "카페",
            "category_name": "음식점 > 카페 > 다방",
            "distance": "5524",
            "id": "9163900",
            "phone": "033-335-5088",
            "place_name": "수다방",
            "place_url": "http://place.map.kakao.com/9163900",
            "road_address_name": "강원 평창군 진부면 진부중앙로 61",
            "x": "128.558210179968",
            "y": "37.6370274524164"
        },
        {
            "address_name": "강원 평창군 진부면 하진부리 121",
            "category_group_code": "CE7",
            "category_group_name": "카페",
            "category_name": "음식점 > 카페 > 다방",
            "distance": "5464",
            "id": "9815211",
            "phone": "033-335-6666",
            "place_name": "서림다방",
            "place_url": "http://place.map.kakao.com/9815211",
            "road_address_name": "강원 평창군 진부면 진부중앙로 48",
            "x": "128.557568948825",
            "y": "37.6358323193218"
        },
        {
            "address_name": "강원 평창군 진부면 상진부리 250-12",
            "category_group_code": "CE7",
            "category_group_name": "카페",
            "category_name": "음식점 > 카페",
            "distance": "5863",
            "id": "1094384101",
            "phone": "033-334-6133",
            "place_name": "카페라온",
            "place_url": "http://place.map.kakao.com/1094384101",
            "road_address_name": "강원 평창군 진부면 경강로 3745",
            "x": "128.568505401746",
            "y": "37.6464981760318"
        },
        {
            "address_name": "강원 평창군 진부면 하진부리 119-1",
            "category_group_code": "CE7",
            "category_group_name": "카페",
            "category_name": "음식점 > 카페 > 다방",
            "distance": "5445",
            "id": "9391733",
            "phone": "033-335-3171",
            "place_name": "정원다방",
            "place_url": "http://place.map.kakao.com/9391733",
            "road_address_name": "강원 평창군 진부면 청송로 110",
            "x": "128.55851662002",
            "y": "37.6362954769782"
        },
        {
            "address_name": "강원 평창군 진부면 하진부리 141",
            "category_group_code": "CE7",
            "category_group_name": "카페",
            "category_name": "음식점 > 카페 > 커피전문점",
            "distance": "5595",
            "id": "373514783",
            "phone": "033-335-3212",
            "place_name": "로드32",
            "place_url": "http://place.map.kakao.com/373514783",
            "road_address_name": "강원 평창군 진부면 진부시장뒷길 32",
            "x": "128.557708649079",
            "y": "37.6375313732601"
        },
        {
            "address_name": "강원 평창군 진부면 하진부리 1291-8",
            "category_group_code": "CE7",
            "category_group_name": "카페",
            "category_name": "음식점 > 카페 > 다방",
            "distance": "5589",
            "id": "26594492",
            "phone": "033-335-4585",
            "place_name": "명다방",
            "place_url": "http://place.map.kakao.com/26594492",
            "road_address_name": "강원 평창군 진부면 진부중앙로 85",
            "x": "128.559867764386",
            "y": "37.6389334683529"
        },
        {
            "address_name": "강원 평창군 진부면 하진부리 206-24",
            "category_group_code": "CE7",
            "category_group_name": "카페",
            "category_name": "음식점 > 카페 > 다방",
            "distance": "5551",
            "id": "9473483",
            "phone": "033-335-3000",
            "place_name": "청솔다방",
            "place_url": "http://place.map.kakao.com/9473483",
            "road_address_name": "강원 평창군 진부면 진부중앙로 73",
            "x": "128.559031224897",
            "y": "37.6379355208934"
        },
        {
            "address_name": "강원 평창군 진부면 하진부리 148-27",
            "category_group_code": "CE7",
            "category_group_name": "카페",
            "category_name": "음식점 > 카페",
            "distance": "5648",
            "id": "276700233",
            "phone": "033-336-5558",
            "place_name": "원지카페",
            "place_url": "http://place.map.kakao.com/276700233",
            "road_address_name": "강원 평창군 진부면 청송로 83-1",
            "x": "128.555693009626",
            "y": "37.6367039213965"
        },
        {
            "address_name": "강원 평창군 진부면 하진부리 77-8",
            "category_group_code": "CE7",
            "category_group_name": "카페",
            "category_name": "음식점 > 카페 > 다방",
            "distance": "5601",
            "id": "10990263",
            "phone": "033-335-7789",
            "place_name": "호수다방",
            "place_url": "http://place.map.kakao.com/10990263",
            "road_address_name": "강원 평창군 진부면 진부중앙로 91-1",
            "x": "128.560187740549",
            "y": "37.6392823888667"
        },
        {
            "address_name": "강원 평창군 진부면 하진부리 75-1",
            "category_group_code": "CE7",
            "category_group_name": "카페",
            "category_name": "음식점 > 카페 > 다방",
            "distance": "5561",
            "id": "11164543",
            "phone": "033-335-7508",
            "place_name": "정다방",
            "place_url": "http://place.map.kakao.com/11164543",
            "road_address_name": "강원 평창군 진부면 진부중앙로 94",
            "x": "128.560797978283",
            "y": "37.6392094508192"
        },
        {
            "address_name": "강원 평창군 진부면 하진부리 138-2",
            "category_group_code": "CE7",
            "category_group_name": "카페",
            "category_name": "음식점 > 카페 > 다방",
            "distance": "5520",
            "id": "12762844",
            "phone": "",
            "place_name": "그곳에",
            "place_url": "http://place.map.kakao.com/12762844",
            "road_address_name": "강원 평창군 진부면 진부중앙로 59",
            "x": "128.558107957143",
            "y": "37.636906280399"
        },
        {
            "address_name": "강원 평창군 진부면 하진부리 152-24",
            "category_group_code": "CE7",
            "category_group_name": "카페",
            "category_name": "음식점 > 카페 > 다방",
            "distance": "5584",
            "id": "9009113",
            "phone": "",
            "place_name": "반도다방",
            "place_url": "http://place.map.kakao.com/9009113",
            "road_address_name": "강원 평창군 진부면 청송로 90-4",
            "x": "128.55638145387394",
            "y": "37.63641646158541"
        }
    ],
    "meta": {
        "is_end": false,
        "pageable_count": 45,
        "same_name": null,
        "total_count": 116935
    }
}